{
  "_class": "shapeGroup",
  "booleanOperation": 0,
  "clippingMaskMode": 0,
  "do_objectID": "F3898F9F-F5FA-4066-AEB1-8F25774CFE6A",
  "exportOptions": {
    "_class": "exportOptions",
    "exportFormats": [
    ],
    "includedLayerIds": [
    ],
    "layerOptions": 0,
    "shouldTrim": false
  },
  "frame": {
    "_class": "rect",
    "constrainProportions": false,
    "height": 11.66153846153836,
    "width": 13.44900909647693,
    "x": 0.2307692307695106,
    "y": 0.4615384615390212
  },
  "groupLayout": {
    "_class": "MSImmutableFreeformGroupLayout"
  },
  "hasClickThrough": false,
  "hasClippingMask": true,
  "isFixedToViewport": false,
  "isFlippedHorizontal": false,
  "isFlippedVertical": false,
  "isLocked": false,
  "isVisible": true,
  "layerListExpandedType": 0,
  "layers": [
    {
      "class": "shapePath",
      "id": "59950FE6-F751-4619-A745-8072222D80D7"
    },
    {
      "class": "shapePath",
      "id": "5655FF4F-8C4A-43BA-84E3-AC0590B75B82"
    },
    {
      "class": "shapePath",
      "id": "5614FD7E-00C9-4188-83CB-3679CFAF7536"
    }
  ],
  "name": "Mask",
  "nameIsFixed": false,
  "resizingConstraint": 63,
  "resizingType": 0,
  "rotation": 0,
  "sharedStyleID": "F85B6AF5-8F7B-4980-B7B9-835035D0D252",
  "shouldBreakMaskChain": false,
  "style": {
    "_class": "style",
    "endMarkerType": 0,
    "fills": [
      {
        "_class": "fill",
        "color": {
          "_class": "color",
          "alpha": 1,
          "blue": 0.5529411764705883,
          "green": 0.4117647058823529,
          "red": 0.3294117647058823
        },
        "fillType": 0,
        "isEnabled": true,
        "noiseIndex": 0,
        "noiseIntensity": 0,
        "patternFillType": 0,
        "patternTileScale": 1
      }
    ],
    "miterLimit": 10,
    "startMarkerType": 0,
    "windingRule": 1
  },
  "windingRule": 1
}