{
  "_class": "shapePath",
  "booleanOperation": -1,
  "clippingMaskMode": 0,
  "do_objectID": "B514C5D0-59D7-4452-A837-EC1B4CB55E3F",
  "edited": true,
  "exportOptions": {
    "_class": "exportOptions",
    "exportFormats": [
    ],
    "includedLayerIds": [
    ],
    "layerOptions": 0,
    "shouldTrim": false
  },
  "frame": {
    "_class": "rect",
    "constrainProportions": false,
    "height": 17.81848811201488,
    "width": 13.15869140624392,
    "x": 3.78955078125,
    "y": 54.9560546875
  },
  "hasClippingMask": false,
  "isClosed": true,
  "isFixedToViewport": false,
  "isFlippedHorizontal": false,
  "isFlippedVertical": false,
  "isLocked": false,
  "isVisible": true,
  "layerListExpandedType": 0,
  "name": "Path 2",
  "nameIsFixed": false,
  "pointRadiusBehaviour": 0,
  "points": [
    {
      "_class": "curvePoint",
      "cornerRadius": 0,
      "curveFrom": "{1.0000000000000002, 0.096157367307442565}",
      "curveMode": 1,
      "curveTo": "{1.0000000000000002, 0.096157367307442565}",
      "hasCurveFrom": false,
      "hasCurveTo": false,
      "point": "{1.0000000000000002, 0.096157367307442565}"
    },
    {
      "_class": "curvePoint",
      "cornerRadius": 0,
      "curveFrom": "{0.28661545882990497, 1.4512117007314373}",
      "curveMode": 2,
      "curveTo": "{0.17388400311602467, 0.22338981427479113}",
      "hasCurveFrom": true,
      "hasCurveTo": true,
      "point": "{0.23024973097296481, 0.83730075750311428}"
    },
    {
      "_class": "curvePoint",
      "cornerRadius": 0,
      "curveFrom": "{0, 0.13000015688411748}",
      "curveMode": 1,
      "curveTo": "{0, 0.13000015688411748}",
      "hasCurveFrom": false,
      "hasCurveTo": false,
      "point": "{0, 0.13000015688411748}"
    },
    {
      "_class": "curvePoint",
      "cornerRadius": 0,
      "curveFrom": "{0.38339084938234358, 0.046804440969245353}",
      "curveMode": 2,
      "curveTo": "{0.072210471631633924, 0.046804440969245374}",
      "hasCurveFrom": true,
      "hasCurveTo": true,
      "point": "{0.22780066050698874, 0.046804440969245353}"
    },
    {
      "_class": "curvePoint",
      "cornerRadius": 0,
      "curveFrom": "{0.99606664440285031, 0}",
      "curveMode": 1,
      "curveTo": "{0.99606664440285031, 0}",
      "hasCurveFrom": false,
      "hasCurveTo": false,
      "point": "{0.99606664440285031, 0}"
    }
  ],
  "resizingConstraint": 63,
  "resizingType": 0,
  "rotation": 0,
  "shouldBreakMaskChain": false,
  "style": {
    "_class": "style",
    "borders": [
      {
        "_class": "border",
        "color": {
          "_class": "color",
          "alpha": 1,
          "blue": 0.592,
          "green": 0.592,
          "red": 0.592
        },
        "fillType": 0,
        "isEnabled": false,
        "position": 0,
        "thickness": 1
      }
    ],
    "endMarkerType": 0,
    "fills": [
      {
        "_class": "fill",
        "color": {
          "_class": "color",
          "alpha": 1,
          "blue": 0.9019607843137255,
          "green": 0.8431372549019608,
          "red": 0.8117647058823529
        },
        "fillType": 0,
        "isEnabled": true,
        "noiseIndex": 0,
        "noiseIntensity": 0,
        "patternFillType": 0,
        "patternTileScale": 1
      }
    ],
    "miterLimit": 10,
    "startMarkerType": 0,
    "windingRule": 1
  }
}