{
  "_class": "oval",
  "booleanOperation": -1,
  "clippingMaskMode": 0,
  "do_objectID": "F3317366-3D5F-4077-961F-88241A6FF4C0",
  "edited": true,
  "exportOptions": {
    "_class": "exportOptions",
    "exportFormats": [
    ],
    "includedLayerIds": [
    ],
    "layerOptions": 0,
    "shouldTrim": false
  },
  "frame": {
    "_class": "rect",
    "constrainProportions": true,
    "height": 20.78452510434977,
    "width": 35.5875402792696,
    "x": 10.08313641245954,
    "y": 9.094947017729282e-13
  },
  "hasClippingMask": false,
  "isClosed": true,
  "isFixedToViewport": false,
  "isFlippedHorizontal": false,
  "isFlippedVertical": false,
  "isLocked": false,
  "isVisible": true,
  "layerListExpandedType": 0,
  "name": "Oval 6",
  "nameIsFixed": false,
  "pointRadiusBehaviour": 0,
  "points": [
    {
      "_class": "curvePoint",
      "cornerRadius": 0,
      "curveFrom": "{0.77614237490000004, 0.48512710114071739}",
      "curveMode": 2,
      "curveTo": "{0.22385762510000001, 0.48512710114071739}",
      "hasCurveFrom": true,
      "hasCurveTo": true,
      "point": "{0.5, 0.48512710114071739}"
    },
    {
      "_class": "curvePoint",
      "cornerRadius": 0,
      "curveFrom": "{1, 0.38329200258708879}",
      "curveMode": 2,
      "curveTo": "{1, 1.328921295556619}",
      "hasCurveFrom": true,
      "hasCurveTo": true,
      "point": "{1, 0.85610664907185452}"
    },
    {
      "_class": "curvePoint",
      "cornerRadius": 0,
      "curveFrom": "{0.22385762510000001, 0}",
      "curveMode": 2,
      "curveTo": "{0.77614237490000004, 0}",
      "hasCurveFrom": true,
      "hasCurveTo": true,
      "point": "{0.5, 0}"
    },
    {
      "_class": "curvePoint",
      "cornerRadius": 0,
      "curveFrom": "{0, 1.328921295556619}",
      "curveMode": 2,
      "curveTo": "{0, 0.38329200258708879}",
      "hasCurveFrom": true,
      "hasCurveTo": true,
      "point": "{0, 0.85610664907185452}"
    }
  ],
  "resizingConstraint": 63,
  "resizingType": 0,
  "rotation": 0,
  "shouldBreakMaskChain": false,
  "style": {
    "_class": "style",
    "borders": [
      {
        "_class": "border",
        "color": {
          "_class": "color",
          "alpha": 1,
          "blue": 0.9019607843137255,
          "green": 0.8431372549019608,
          "red": 0.8117647058823529
        },
        "fillType": 0,
        "isEnabled": false,
        "position": 0,
        "thickness": 6
      }
    ],
    "endMarkerType": 0,
    "fills": [
      {
        "_class": "fill",
        "color": {
          "_class": "color",
          "alpha": 1,
          "blue": 0.9764705882352941,
          "green": 0.9647058823529412,
          "red": 0.9568627450980393
        },
        "fillType": 0,
        "isEnabled": true,
        "noiseIndex": 0,
        "noiseIntensity": 0,
        "patternFillType": 0,
        "patternTileScale": 1
      }
    ],
    "miterLimit": 10,
    "startMarkerType": 0,
    "windingRule": 1
  }
}