{
  "_class": "shapePath",
  "booleanOperation": -1,
  "clippingMaskMode": 0,
  "do_objectID": "296F62B7-FD7A-4ED0-B38E-448F830526E0",
  "edited": true,
  "exportOptions": {
    "_class": "exportOptions",
    "exportFormats": [
    ],
    "includedLayerIds": [
    ],
    "layerOptions": 0,
    "shouldTrim": false
  },
  "frame": {
    "_class": "rect",
    "constrainProportions": false,
    "height": 30.00000000000001,
    "width": 26.20312500000002,
    "x": 2.000000000000001,
    "y": 0
  },
  "hasClippingMask": false,
  "isClosed": true,
  "isFixedToViewport": false,
  "isFlippedHorizontal": false,
  "isFlippedVertical": false,
  "isLocked": false,
  "isVisible": true,
  "layerListExpandedType": 0,
  "name": "Shape",
  "nameIsFixed": false,
  "pointRadiusBehaviour": 0,
  "points": [
    {
      "_class": "curvePoint",
      "cornerRadius": 0,
      "curveFrom": "{0.041144901610017888, 5.5511151231257827e-17}",
      "curveMode": 4,
      "curveTo": "{0.091234347048300538, 5.5511151231257827e-17}",
      "hasCurveFrom": true,
      "hasCurveTo": false,
      "point": "{0.091234347048300538, 5.5511151231257827e-17}"
    },
    {
      "_class": "curvePoint",
      "cornerRadius": 0,
      "curveFrom": "{0, 0.07968750000000005}",
      "curveMode": 4,
      "curveTo": "{0, 0.035937500000000053}",
      "hasCurveFrom": false,
      "hasCurveTo": true,
      "point": "{0, 0.07968750000000005}"
    },
    {
      "_class": "curvePoint",
      "cornerRadius": 0,
      "curveFrom": "{0, 0.96406250000000004}",
      "curveMode": 4,
      "curveTo": "{0, 0.92031250000000009}",
      "hasCurveFrom": true,
      "hasCurveTo": false,
      "point": "{0, 0.92031250000000009}"
    },
    {
      "_class": "curvePoint",
      "cornerRadius": 0,
      "curveFrom": "{0.091234347048300538, 1}",
      "curveMode": 4,
      "curveTo": "{0.041144901610017888, 1}",
      "hasCurveFrom": false,
      "hasCurveTo": true,
      "point": "{0.091234347048300538, 1}"
    },
    {
      "_class": "curvePoint",
      "cornerRadius": 0,
      "curveFrom": "{0.95885509838998229, 1}",
      "curveMode": 4,
      "curveTo": "{0.90876565295169964, 1}",
      "hasCurveFrom": true,
      "hasCurveTo": false,
      "point": "{0.90876565295169964, 1}"
    },
    {
      "_class": "curvePoint",
      "cornerRadius": 0,
      "curveFrom": "{1.0000000000000002, 0.92031250000000009}",
      "curveMode": 4,
      "curveTo": "{1.0000000000000002, 0.96406250000000004}",
      "hasCurveFrom": false,
      "hasCurveTo": true,
      "point": "{1.0000000000000002, 0.92031250000000009}"
    },
    {
      "_class": "curvePoint",
      "cornerRadius": 0,
      "curveFrom": "{1.0000000000000002, 0.31718750000000001}",
      "curveMode": 1,
      "curveTo": "{1.0000000000000002, 0.31718750000000001}",
      "hasCurveFrom": false,
      "hasCurveTo": false,
      "point": "{1.0000000000000002, 0.31718750000000001}"
    },
    {
      "_class": "curvePoint",
      "cornerRadius": 0,
      "curveFrom": "{0.66189624329159225, 0}",
      "curveMode": 1,
      "curveTo": "{0.66189624329159225, 0}",
      "hasCurveFrom": false,
      "hasCurveTo": false,
      "point": "{0.66189624329159225, 0}"
    },
    {
      "_class": "curvePoint",
      "cornerRadius": 0,
      "curveFrom": "{0.09123434704830069, 0}",
      "curveMode": 1,
      "curveTo": "{0.09123434704830069, 0}",
      "hasCurveFrom": false,
      "hasCurveTo": false,
      "point": "{0.09123434704830069, 0}"
    }
  ],
  "resizingConstraint": 63,
  "resizingType": 0,
  "rotation": 0,
  "shouldBreakMaskChain": false,
  "style": {
    "_class": "style",
    "blur": {
      "_class": "blur",
      "center": "{0.5, 0.5}",
      "isEnabled": false,
      "motionAngle": 0,
      "radius": 5,
      "saturation": 1,
      "type": 0
    },
    "endMarkerType": 0,
    "fills": [
      {
        "_class": "fill",
        "color": {
          "_class": "color",
          "alpha": 1,
          "blue": 0.396078431372549,
          "green": 0.8509803921568627,
          "red": 0.8666666666666667
        },
        "fillType": 0,
        "isEnabled": true,
        "noiseIndex": 0,
        "noiseIntensity": 0,
        "patternFillType": 1,
        "patternTileScale": 1
      }
    ],
    "miterLimit": 10,
    "startMarkerType": 0,
    "windingRule": 1
  }
}