{
  "_class": "shapePath",
  "booleanOperation": -1,
  "clippingMaskMode": 0,
  "do_objectID": "BC7C1CD6-4BE4-40B8-99F6-D04773A94CBA",
  "edited": true,
  "exportOptions": {
    "_class": "exportOptions",
    "exportFormats": [
    ],
    "includedLayerIds": [
    ],
    "layerOptions": 0,
    "shouldTrim": false
  },
  "frame": {
    "_class": "rect",
    "constrainProportions": false,
    "height": 11.5390625,
    "width": 7.3671875,
    "x": 6.824999988079071,
    "y": 0
  },
  "hasClippingMask": false,
  "isClosed": true,
  "isFixedToViewport": false,
  "isFlippedHorizontal": false,
  "isFlippedVertical": false,
  "isLocked": false,
  "isVisible": true,
  "layerListExpandedType": 0,
  "name": "Path",
  "nameIsFixed": false,
  "pointRadiusBehaviour": 0,
  "points": [
    {
      "_class": "curvePoint",
      "cornerRadius": 0,
      "curveFrom": "{0, 0.29790115098171971}",
      "curveMode": 4,
      "curveTo": "{0, 0.2112385646580906}",
      "hasCurveFrom": false,
      "hasCurveTo": true,
      "point": "{0, 0.29790115098171971}"
    },
    {
      "_class": "curvePoint",
      "cornerRadius": 0,
      "curveFrom": "{0, 0.29857819905213268}",
      "curveMode": 1,
      "curveTo": "{0, 0.29857819905213268}",
      "hasCurveFrom": false,
      "hasCurveTo": false,
      "point": "{0, 0.29857819905213268}"
    },
    {
      "_class": "curvePoint",
      "cornerRadius": 0,
      "curveFrom": "{0.18451749734888653, 0.29857819905213268}",
      "curveMode": 1,
      "curveTo": "{0.18451749734888653, 0.29857819905213268}",
      "hasCurveFrom": false,
      "hasCurveTo": false,
      "point": "{0.18451749734888653, 0.29857819905213268}"
    },
    {
      "_class": "curvePoint",
      "cornerRadius": 0,
      "curveFrom": "{0.18451749734888653, 0.24012609343263372}",
      "curveMode": 4,
      "curveTo": "{0.18451749734888653, 0.29790115098171971}",
      "hasCurveFrom": true,
      "hasCurveTo": false,
      "point": "{0.18451749734888653, 0.29790115098171971}"
    },
    {
      "_class": "curvePoint",
      "cornerRadius": 0,
      "curveFrom": "{0.32237567338282058, 0.12378678063642519}",
      "curveMode": 2,
      "curveTo": "{0.21208880169671282, 0.19374876438727148}",
      "hasCurveFrom": true,
      "hasCurveTo": true,
      "point": "{0.26723223753976671, 0.15876777251184834}"
    },
    {
      "_class": "curvePoint",
      "cornerRadius": 0,
      "curveFrom": "{0.56875262990455977, 0.10629654705484089}",
      "curveMode": 2,
      "curveTo": "{0.39483871686108174, 0.10629654705484089}",
      "hasCurveFrom": true,
      "hasCurveTo": true,
      "point": "{0.48462354188759277, 0.10629654705484089}"
    },
    {
      "_class": "curvePoint",
      "cornerRadius": 0,
      "curveFrom": "{0.75486066277836672, 0.18923510155721038}",
      "curveMode": 2,
      "curveTo": "{0.63962502120890796, 0.12288405890318201}",
      "hasCurveFrom": true,
      "hasCurveTo": true,
      "point": "{0.69724284199363729, 0.15605958023019634}"
    },
    {
      "_class": "curvePoint",
      "cornerRadius": 0,
      "curveFrom": "{0.78366914103923646, 0.31821278943805009}",
      "curveMode": 2,
      "curveTo": "{0.78366914103923646, 0.23019610020311443}",
      "hasCurveFrom": true,
      "hasCurveTo": true,
      "point": "{0.78366914103923646, 0.2789438050101557}"
    },
    {
      "_class": "curvePoint",
      "cornerRadius": 0,
      "curveFrom": "{0.70325187168610803, 0.42642762017603253}",
      "curveMode": 2,
      "curveTo": "{0.76758588016967133, 0.35556290115098166}",
      "hasCurveFrom": true,
      "hasCurveTo": true,
      "point": "{0.73541887592788968, 0.39099526066350709}"
    },
    {
      "_class": "curvePoint",
      "cornerRadius": 0,
      "curveFrom": "{0.53870625662778371, 0.54705484089370349}",
      "curveMode": 4,
      "curveTo": "{0.63768165429480372, 0.47844696005416371}",
      "hasCurveFrom": false,
      "hasCurveTo": true,
      "point": "{0.53870625662778371, 0.54705484089370349}"
    },
    {
      "_class": "curvePoint",
      "cornerRadius": 0,
      "curveFrom": "{0.0095440084835630972, 0.91604603926878814}",
      "curveMode": 1,
      "curveTo": "{0.0095440084835630972, 0.91604603926878814}",
      "hasCurveFrom": false,
      "hasCurveTo": false,
      "point": "{0.0095440084835630972, 0.91604603926878814}"
    },
    {
      "_class": "curvePoint",
      "cornerRadius": 0,
      "curveFrom": "{0.0095440084835630972, 1}",
      "curveMode": 1,
      "curveTo": "{0.0095440084835630972, 1}",
      "hasCurveFrom": false,
      "hasCurveTo": false,
      "point": "{0.0095440084835630972, 1}"
    },
    {
      "_class": "curvePoint",
      "cornerRadius": 0,
      "curveFrom": "{1, 1}",
      "curveMode": 1,
      "curveTo": "{1, 1}",
      "hasCurveFrom": false,
      "hasCurveTo": false,
      "point": "{1, 1}"
    },
    {
      "_class": "curvePoint",
      "cornerRadius": 0,
      "curveFrom": "{1, 0.89031821259309407}",
      "curveMode": 1,
      "curveTo": "{1, 0.89031821259309407}",
      "hasCurveFrom": false,
      "hasCurveTo": false,
      "point": "{1, 0.89031821259309407}"
    },
    {
      "_class": "curvePoint",
      "cornerRadius": 0,
      "curveFrom": "{0.2831389183457052, 0.89031821259309407}",
      "curveMode": 1,
      "curveTo": "{0.2831389183457052, 0.89031821259309407}",
      "hasCurveFrom": false,
      "hasCurveTo": false,
      "point": "{0.2831389183457052, 0.89031821259309407}"
    },
    {
      "_class": "curvePoint",
      "cornerRadius": 0,
      "curveFrom": "{0.2831389183457052, 0.87948544346648616}",
      "curveMode": 1,
      "curveTo": "{0.2831389183457052, 0.87948544346648616}",
      "hasCurveFrom": false,
      "hasCurveTo": false,
      "point": "{0.2831389183457052, 0.87948544346648616}"
    },
    {
      "_class": "curvePoint",
      "cornerRadius": 0,
      "curveFrom": "{0.77695361611877012, 0.54073529451591051}",
      "curveMode": 4,
      "curveTo": "{0.65111346765641565, 0.62694651320243733}",
      "hasCurveFrom": true,
      "hasCurveTo": false,
      "point": "{0.65111346765641565, 0.62694651320243733}"
    },
    {
      "_class": "curvePoint",
      "cornerRadius": 0,
      "curveFrom": "{0.952103441145281, 0.37463301963439399}",
      "curveMode": 2,
      "curveTo": "{0.86231861611876992, 0.47303116452268118}",
      "hasCurveFrom": true,
      "hasCurveTo": true,
      "point": "{0.90721102863202541, 0.42383209207853756}"
    },
    {
      "_class": "curvePoint",
      "cornerRadius": 0,
      "curveFrom": "{0.97454931071049844, 0.1965692349356806}",
      "curveMode": 3,
      "curveTo": "{0.97454931071049844, 0.32475764387271516}",
      "hasCurveFrom": true,
      "hasCurveTo": true,
      "point": "{0.97454931071049844, 0.27420446851726471}"
    },
    {
      "_class": "curvePoint",
      "cornerRadius": 0,
      "curveFrom": "{0.7421345652173913, 0.026291770480704205}",
      "curveMode": 2,
      "curveTo": "{0.9280669194061506, 0.13146042992552465}",
      "hasCurveFrom": true,
      "hasCurveTo": true,
      "point": "{0.83510074231177089, 0.078876100203114419}"
    },
    {
      "_class": "curvePoint",
      "cornerRadius": 0,
      "curveFrom": "{0.34782537645811201, 0}",
      "curveMode": 2,
      "curveTo": "{0.62707739130434814, 0}",
      "hasCurveFrom": true,
      "hasCurveTo": true,
      "point": "{0.48992576882290562, 0}"
    },
    {
      "_class": "curvePoint",
      "cornerRadius": 0,
      "curveFrom": "{0.04612891304347834, 0.13992354773188909}",
      "curveMode": 2,
      "curveTo": "{0.23064733297985146, 0.027984373730534907}",
      "hasCurveFrom": true,
      "hasCurveTo": true,
      "point": "{0.13838812301166489, 0.083953960731211918}"
    }
  ],
  "resizingConstraint": 63,
  "resizingType": 0,
  "rotation": 0,
  "shouldBreakMaskChain": false,
  "style": {
    "_class": "style",
    "blur": {
      "_class": "blur",
      "center": "{0.5, 0.5}",
      "isEnabled": false,
      "motionAngle": 0,
      "radius": 5,
      "saturation": 1,
      "type": 0
    },
    "endMarkerType": 0,
    "fills": [
      {
        "_class": "fill",
        "color": {
          "_class": "color",
          "alpha": 1,
          "blue": 0,
          "green": 0,
          "red": 0
        },
        "fillType": 0,
        "isEnabled": true,
        "noiseIndex": 0,
        "noiseIntensity": 0,
        "patternFillType": 1,
        "patternTileScale": 1
      }
    ],
    "miterLimit": 10,
    "startMarkerType": 0,
    "textStyle": {
      "_class": "textStyle",
      "encodedAttributes": {
        "MSAttributedStringColorAttribute": {
          "_class": "color",
          "alpha": 1,
          "blue": 0,
          "green": 0,
          "red": 0
        },
        "MSAttributedStringFontAttribute": {
          "_class": "fontDescriptor",
          "attributes": {
            "name": "SFUIText-Regular",
            "size": 16
          }
        },
        "kerning": -0.550000011920929,
        "paragraphStyle": {
          "_class": "paragraphStyle",
          "allowsDefaultTighteningForTruncation": 0
        }
      },
      "verticalAlignment": 0
    },
    "windingRule": 1
  }
}