{
  "_class": "shapePath",
  "booleanOperation": -1,
  "clippingMaskMode": 0,
  "do_objectID": "2154FB44-C0A6-4B64-A490-A421B3209C7F",
  "edited": true,
  "exportOptions": {
    "_class": "exportOptions",
    "exportFormats": [
    ],
    "includedLayerIds": [
    ],
    "layerOptions": 0,
    "shouldTrim": false
  },
  "frame": {
    "_class": "rect",
    "constrainProportions": true,
    "height": 6.829268292682934,
    "width": 11.85288461538462,
    "x": 68,
    "y": 7
  },
  "hasClippingMask": false,
  "isClosed": true,
  "isFixedToViewport": false,
  "isFlippedHorizontal": false,
  "isFlippedVertical": false,
  "isLocked": false,
  "isVisible": true,
  "layerListExpandedType": 0,
  "name": "Fill 1",
  "nameIsFixed": false,
  "pointRadiusBehaviour": 0,
  "points": [
    {
      "_class": "curvePoint",
      "cornerRadius": 0,
      "curveFrom": "{0.51220897217490069, 1.0057692307692307}",
      "curveMode": 4,
      "curveTo": "{0.52583759227711535, 0.98269230769230786}",
      "hasCurveFrom": true,
      "hasCurveTo": false,
      "point": "{0.52583759227711535, 0.98269230769230786}"
    },
    {
      "_class": "curvePoint",
      "cornerRadius": 0,
      "curveFrom": "{0.47586598523566154, 0.98269230769230786}",
      "curveMode": 4,
      "curveTo": "{0.48949460533787625, 1.0057692307692307}",
      "hasCurveFrom": false,
      "hasCurveTo": true,
      "point": "{0.47586598523566154, 0.98269230769230786}"
    },
    {
      "_class": "curvePoint",
      "cornerRadius": 0,
      "curveFrom": "{-0.0034071550255536701, 0.16346153846153838}",
      "curveMode": 4,
      "curveTo": "{0.010221465076661012, 0.18653846153846151}",
      "hasCurveFrom": true,
      "hasCurveTo": false,
      "point": "{0.010221465076661012, 0.18653846153846151}"
    },
    {
      "_class": "curvePoint",
      "cornerRadius": 0,
      "curveFrom": "{0.010221465076661012, 0.10192307692307694}",
      "curveMode": 4,
      "curveTo": "{-0.0034071550255536701, 0.12499999999999993}",
      "hasCurveFrom": false,
      "hasCurveTo": true,
      "point": "{0.010221465076661012, 0.10192307692307694}"
    },
    {
      "_class": "curvePoint",
      "cornerRadius": 0,
      "curveFrom": "{0.073844406587166442, -0.0057692307692307826}",
      "curveMode": 4,
      "curveTo": "{0.060193072118114789, 0.01730769230769235}",
      "hasCurveFrom": true,
      "hasCurveTo": false,
      "point": "{0.060193072118114789, 0.01730769230769235}"
    },
    {
      "_class": "curvePoint",
      "cornerRadius": 0,
      "curveFrom": "{0.1101646791595684, 0.01730769230769235}",
      "curveMode": 4,
      "curveTo": "{0.09655877342419085, -0.0057692307692307826}",
      "hasCurveFrom": false,
      "hasCurveTo": true,
      "point": "{0.1101646791595684, 0.01730769230769235}"
    },
    {
      "_class": "curvePoint",
      "cornerRadius": 0,
      "curveFrom": "{0.48949460533787625, 0.66730769230769238}",
      "curveMode": 4,
      "curveTo": "{0.47586598523566154, 0.64423076923076927}",
      "hasCurveFrom": true,
      "hasCurveTo": false,
      "point": "{0.47586598523566154, 0.64423076923076927}"
    },
    {
      "_class": "curvePoint",
      "cornerRadius": 0,
      "curveFrom": "{0.52583759227711535, 0.64423076923076927}",
      "curveMode": 4,
      "curveTo": "{0.51220897217490069, 0.66730769230769238}",
      "hasCurveFrom": false,
      "hasCurveTo": true,
      "point": "{0.52583759227711535, 0.64423076923076927}"
    },
    {
      "_class": "curvePoint",
      "cornerRadius": 0,
      "curveFrom": "{0.90516751845542309, -0.001923076923076882}",
      "curveMode": 4,
      "curveTo": "{0.89156161272004542, 0.021153846153846113}",
      "hasCurveFrom": true,
      "hasCurveTo": false,
      "point": "{0.89156161272004542, 0.021153846153846113}"
    },
    {
      "_class": "curvePoint",
      "cornerRadius": 0,
      "curveFrom": "{0.94153321976149917, 0.021153846153846113}",
      "curveMode": 4,
      "curveTo": "{0.92788188529244753, -0.001923076923076882}",
      "hasCurveFrom": false,
      "hasCurveTo": true,
      "point": "{0.94153321976149917, 0.021153846153846113}"
    },
    {
      "_class": "curvePoint",
      "cornerRadius": 0,
      "curveFrom": "{1.0028392958546279, 0.12884615384615383}",
      "curveMode": 4,
      "curveTo": "{0.99148211243611584, 0.1057692307692307}",
      "hasCurveFrom": true,
      "hasCurveTo": false,
      "point": "{0.99148211243611584, 0.1057692307692307}"
    },
    {
      "_class": "curvePoint",
      "cornerRadius": 0,
      "curveFrom": "{0.99148211243611584, 0.18653846153846151}",
      "curveMode": 4,
      "curveTo": "{1.0028392958546279, 0.16346153846153838}",
      "hasCurveFrom": false,
      "hasCurveTo": true,
      "point": "{0.99148211243611584, 0.18653846153846151}"
    }
  ],
  "resizingConstraint": 63,
  "resizingType": 0,
  "rotation": 0,
  "shouldBreakMaskChain": false,
  "style": {
    "_class": "style",
    "endMarkerType": 0,
    "fills": [
      {
        "_class": "fill",
        "color": {
          "_class": "color",
          "alpha": 1,
          "blue": 0.360784322,
          "green": 0.1960784346,
          "red": 0.08627451211
        },
        "fillType": 0,
        "isEnabled": true,
        "noiseIndex": 0,
        "noiseIntensity": 0,
        "patternFillType": 1,
        "patternTileScale": 1
      }
    ],
    "miterLimit": 10,
    "startMarkerType": 0,
    "windingRule": 1
  },
  "userInfo": {
    "com.animaapp.stc-sketch-plugin": {
      "kModelPropertiesKey": {
      }
    }
  }
}