{
  "_class": "group",
  "booleanOperation": 0,
  "clippingMaskMode": 0,
  "do_objectID": "46E7AAF7-FD9F-4079-9808-E89A67FC8C91",
  "exportOptions": {
    "_class": "exportOptions",
    "exportFormats": [
    ],
    "includedLayerIds": [
    ],
    "layerOptions": 0,
    "shouldTrim": false
  },
  "frame": {
    "_class": "rect",
    "constrainProportions": true,
    "height": 4,
    "width": 6,
    "x": 32,
    "y": 14
  },
  "groupLayout": {
    "_class": "MSImmutableFreeformGroupLayout"
  },
  "hasClickThrough": false,
  "hasClippingMask": false,
  "isFixedToViewport": false,
  "isFlippedHorizontal": false,
  "isFlippedVertical": false,
  "isLocked": false,
  "isVisible": true,
  "layerListExpandedType": 2,
  "layers": [
    {
      "class": "shapePath",
      "id": "5E6FF5EF-EC0F-4B8B-A315-9C521998D2F1"
    }
  ],
  "name": "down",
  "nameIsFixed": false,
  "resizingConstraint": 63,
  "resizingType": 0,
  "rotation": 0,
  "shouldBreakMaskChain": false,
  "style": {
    "_class": "style",
    "endMarkerType": 0,
    "miterLimit": 10,
    "startMarkerType": 0,
    "windingRule": 1
  },
  "userInfo": {
    "com.animaapp.stc-sketch-plugin": {
      "kModelPropertiesKey": {
        "constraints": {
          "aspectRatio": {
            "constant": 4,
            "enabled": 1,
            "modelID": "constraint_29fcc244-2d08-4bb0-ac10-94fd0cb4a5c7",
            "model_class": "ADModelConstraint",
            "model_version": 0.1,
            "multiplier": 6
          },
          "automatic": 1,
          "modelID": "viewConstraints_6df194f0-e9cf-45fd-b290-a9073bf6c797",
          "model_class": "ADModelViewConstraints",
          "model_version": 0.1
        }
      }
    }
  }
}