{
  "_class": "group",
  "booleanOperation": 0,
  "clippingMaskMode": 0,
  "do_objectID": "43A9D7AC-C2A3-4EA1-B536-A3625B873995",
  "exportOptions": {
    "_class": "exportOptions",
    "exportFormats": [
    ],
    "includedLayerIds": [
    ],
    "layerOptions": 0,
    "shouldTrim": false
  },
  "frame": {
    "_class": "rect",
    "constrainProportions": false,
    "height": 50,
    "width": 140,
    "x": 105.0786516853932,
    "y": 90.94488188976356
  },
  "groupLayout": {
    "_class": "MSImmutableFreeformGroupLayout"
  },
  "hasClickThrough": false,
  "hasClippingMask": false,
  "isFixedToViewport": false,
  "isFlippedHorizontal": true,
  "isFlippedVertical": false,
  "isLocked": false,
  "isVisible": true,
  "layerListExpandedType": 2,
  "layers": [
    {
      "class": "rectangle",
      "id": "BA87A4D8-9E08-446E-A5CD-DD206D23F35B"
    },
    {
      "class": "rectangle",
      "id": "BCB0EB1D-AFD7-43F9-A686-A4F2FF7192D5"
    },
    {
      "class": "rectangle",
      "id": "CC687E72-3979-40A6-93D6-467A27211BD5"
    },
    {
      "class": "rectangle",
      "id": "C758B550-BAE0-42C0-9699-DD3714211426"
    },
    {
      "class": "oval",
      "id": "15A604BF-3286-4675-8DF3-E9200BDDE212"
    },
    {
      "class": "oval",
      "id": "A0DF042E-D200-402C-8475-84BAF27B0806"
    },
    {
      "class": "oval",
      "id": "FB75BDD0-C7EE-4263-8446-9805AD9F27CA"
    }
  ],
  "name": "Group 19",
  "nameIsFixed": false,
  "resizingConstraint": 63,
  "resizingType": 0,
  "rotation": 0,
  "shouldBreakMaskChain": false,
  "style": {
    "_class": "style",
    "contextSettings": {
      "_class": "graphicsContextSettings",
      "blendMode": 0,
      "opacity": 0.5
    },
    "endMarkerType": 0,
    "miterLimit": 10,
    "startMarkerType": 0,
    "windingRule": 1
  }
}